pyphenomd/__init__.py
pyphenomd/phenomd.cpython-35m-darwin.so
pyphenomd/pyphenomd.py
pyphenomd/read_noise_curves.py
pyphenomd/noise_curves/CL.txt
pyphenomd/noise_curves/CLLF.txt
pyphenomd/noise_curves/LPA.txt
pyphenomd/noise_curves/PL.txt
pyphenomd/noise_curves/PLCS.txt
pyphenomd/noise_curves/PLHB.txt
pyphenomd/noise_curves/WDnoise.txt
pyphenomd/phenomd/phenomd.c
pyphenomd/phenomd/phenomd.h
pyphenomd/phenomd/ringdown_spectrum_fitting.h
pyphenomd-1.0.2.dist-info/METADATA
pyphenomd-1.0.2.dist-info/RECORD
pyphenomd-1.0.2.dist-info/WHEEL
pyphenomd-1.0.2.dist-info/top_level.txt
