Metadata-Version: 2.1
Name: pyphenomd
Version: 1.0.2
Summary: Python implementation of phenomd amplitude calculation for fast SNR determination
Home-page: https://github.com/mikekatz04/BOWIE/pyphenomd_folder
Author: Michael Katz
Author-email: mikekatz04@gmail.com
License: UNKNOWN
Platform: UNKNOWN
Classifier: Programming Language :: Python :: 3
Classifier: Operating System :: OS Independent
Requires-Dist: numpy
Requires-Dist: scipy
Requires-Dist: astropy
